[
    {
        "date": "2007-12-31", 
        "max_kn": 0.7819577735124761, 
        "min_kn": 0.7819577735124761
    }, 
    {
        "date": "2008-12-31", 
        "max_kn": 0.12203832752613242, 
        "min_kn": 0.04881533101045296
    }, 
    {
        "date": "2009-12-31", 
        "max_kn": -21.539189189189187, 
        "min_kn": -20.224590787971067
    }, 
    {
        "date": "2011-12-31", 
        "max_kn": 1.616449753372556, 
        "min_kn": 1.616449753372556
    }, 
    {
        "date": "2012-12-31", 
        "max_kn": 11.172169629800663, 
        "min_kn": 11.172169629800663
    }, 
    {
        "date": "2013-12-31", 
        "max_kn": 8.549897446691359, 
        "min_kn": 4.270885083874818
    }, 
    {
        "date": "2014-12-31", 
        "max_kn": 6.466177726310372, 
        "min_kn": 3.5702821801713713
    }
]