[
    {
        "date": "2011", 
        "cash_dividends": 0.29524058, 
        "stock_dividends_from_retained_earnings": 2.95240579
    }, 
    {
        "date": "2012", 
        "cash_dividends": 0.34234078, 
        "stock_dividends_from_retained_earnings": 2.9343495321
    }, 
    {
        "date": "2013", 
        "cash_dividends": 0.98735441, 
        "stock_dividends_from_retained_earnings": 1.48103169
    }, 
    {
        "date": "2014", 
        "cash_dividends": 0.999712, 
        "stock_dividends_from_retained_earnings": 0.99971
    }
]