[
    {
        "date": "2013-09-30", 
        "max_kn": 4.160197085852283, 
        "min_kn": 2.8332376705373306
    }, 
    {
        "date": "2013-12-31", 
        "max_kn": -22.418749605580608, 
        "min_kn": -16.593790646925388
    }, 
    {
        "date": "2014-03-31", 
        "max_kn": 4.196685577382595, 
        "min_kn": 2.5783156259872535
    }, 
    {
        "date": "2014-06-30", 
        "max_kn": 5.141856925418571, 
        "min_kn": 3.944037982565379
    }, 
    {
        "date": "2014-09-30", 
        "max_kn": 1.9408163297749008, 
        "min_kn": 1.5589025618406627
    }, 
    {
        "date": "2014-12-31", 
        "max_kn": 1.9122199308719172, 
        "min_kn": 1.1630292863138898
    }, 
    {
        "date": "2015-03-31", 
        "max_kn": 0.12488611184688675, 
        "min_kn": 0.11319805266121656
    }, 
    {
        "date": "2015-06-30", 
        "max_kn": 2.2202096590187614, 
        "min_kn": 1.5605400352003598
    }, 
    {
        "date": "2015-09-30", 
        "max_kn": 15.521561300967738, 
        "min_kn": 10.241577200296662
    }
]