[
    {
        "date": "2013-09-30", 
        "max_kn": 2.8403875053549448, 
        "min_kn": 2.0615724337844523
    }, 
    {
        "date": "2013-12-31", 
        "max_kn": 1.5763302448761396, 
        "min_kn": 1.3355044227751671
    }, 
    {
        "date": "2014-03-31", 
        "max_kn": 15.273561380667394, 
        "min_kn": 12.777857827465239
    }, 
    {
        "date": "2014-06-30", 
        "max_kn": 16.19493275768073, 
        "min_kn": 10.411033016130835
    }, 
    {
        "date": "2014-09-30", 
        "max_kn": 1.479006173539086, 
        "min_kn": 1.1051944532914453
    }, 
    {
        "date": "2015-03-31", 
        "max_kn": 17.725458661461584, 
        "min_kn": 15.151617247174151
    }, 
    {
        "date": "2015-06-30", 
        "max_kn": 16.341719480060124, 
        "min_kn": 8.315909468654672
    }, 
    {
        "date": "2015-09-30", 
        "max_kn": 2.503401360544218, 
        "min_kn": 1.4661354581673305
    }
]