[
    {
        "dio": 76.39911308203992, 
        "net_profit_margin": -1.2987012987012987, 
        "net_profit_before_tax_margin": -1.1363636363636365, 
        "operating_profit_margin": 0.8522727272727272, 
        "dso": 38.81087662337662, 
        "date": "2007-12-31", 
        "dpo": 26.707317073170735, 
        "gross_profit_margin": 8.522727272727272, 
        "ccc": 88.5026726322458
    }, 
    {
        "dio": 74.81192425793245, 
        "net_profit_margin": 1.335240820219361, 
        "net_profit_before_tax_margin": 1.2875536480686696, 
        "operating_profit_margin": -0.9060562708631379, 
        "dso": 39.946351931330476, 
        "date": "2008-12-31", 
        "dpo": 24.003326509723646, 
        "gross_profit_margin": 6.819265617548879, 
        "ccc": 90.75494967953927
    }, 
    {
        "dio": 70.61395759717315, 
        "net_profit_margin": 2.320675105485232, 
        "net_profit_before_tax_margin": 2.5843881856540083, 
        "operating_profit_margin": 1.6877637130801686, 
        "dso": 38.59836497890295, 
        "date": "2009-12-31", 
        "dpo": 22.248233215547707, 
        "gross_profit_margin": 10.390295358649789, 
        "ccc": 86.96408936052839
    }, 
    {
        "dio": 66.1087710604559, 
        "net_profit_margin": 5.119926199261993, 
        "net_profit_before_tax_margin": 5.258302583025831, 
        "operating_profit_margin": -0.46125461254612543, 
        "dso": 41.66858856088561, 
        "date": "2010-12-31", 
        "dpo": 18.99157581764123, 
        "gross_profit_margin": 6.872693726937269, 
        "ccc": 88.78578380370027
    }, 
    {
        "dio": 66.36363636363636, 
        "net_profit_margin": 4.4608055435253355, 
        "net_profit_before_tax_margin": 4.677349501948895, 
        "operating_profit_margin": 2.858380251190992, 
        "dso": 47.81831961888263, 
        "date": "2011-12-31", 
        "dpo": 24.624401913875595, 
        "gross_profit_margin": 9.484625378951927, 
        "ccc": 89.55755406864338
    }, 
    {
        "dio": 78.80463401790416, 
        "net_profit_margin": 1.1252446183953033, 
        "net_profit_before_tax_margin": 1.223091976516634, 
        "operating_profit_margin": 0.29354207436399216, 
        "dso": 53.92857142857142, 
        "date": "2012-12-31", 
        "dpo": 31.810163243812536, 
        "gross_profit_margin": 7.0939334637964775, 
        "ccc": 100.92304220266304
    }, 
    {
        "dio": 94.60477941176471, 
        "net_profit_margin": 3.114518447532343, 
        "net_profit_before_tax_margin": 3.210349784379492, 
        "operating_profit_margin": 2.156205079060853, 
        "dso": 52.72999520843316, 
        "date": "2013-12-31", 
        "dpo": 23.962710084033613, 
        "gross_profit_margin": 8.768567321514135, 
        "ccc": 123.37206453616425
    }, 
    {
        "dio": 113.2652198421646, 
        "net_profit_margin": 1.5191199580932426, 
        "net_profit_before_tax_margin": 1.5715034049240442, 
        "operating_profit_margin": 0.47145102147721324, 
        "dso": 56.117077003666836, 
        "date": "2014-12-31", 
        "dpo": 17.488726042841037, 
        "gross_profit_margin": 7.071765322158198, 
        "ccc": 151.89357080299038
    }
]