[
    {
        "dio": 33.412386706948645, 
        "net_profit_margin": 8.431372549019608, 
        "net_profit_before_tax_margin": 9.859943977591037, 
        "operating_profit_margin": 3.1372549019607843, 
        "dso": 17.176470588235293, 
        "date": "2007-12-31", 
        "dpo": 7.498489425981872, 
        "gross_profit_margin": 7.254901960784315, 
        "ccc": 43.09036786920207
    }, 
    {
        "dio": 30.754750806740766, 
        "net_profit_margin": -16.721431179262506, 
        "net_profit_before_tax_margin": -13.179992698064988, 
        "operating_profit_margin": -6.973347937203359, 
        "dso": 25.119569185834248, 
        "date": "2008-12-31", 
        "dpo": 5.365722481176048, 
        "gross_profit_margin": -1.8254837531945967, 
        "ccc": 50.50859751139896
    }, 
    {
        "dio": 37.31223922114047, 
        "net_profit_margin": 6.146878032999029, 
        "net_profit_before_tax_margin": 6.243934001941119, 
        "operating_profit_margin": 2.7175671303785185, 
        "dso": 34.00841151730831, 
        "date": "2009-12-31", 
        "dpo": 9.264603616133519, 
        "gross_profit_margin": 6.988029763830475, 
        "ccc": 62.05604712231527
    }, 
    {
        "dio": 38.93160878809355, 
        "net_profit_margin": 13.436637656548504, 
        "net_profit_before_tax_margin": 14.200806622797707, 
        "operating_profit_margin": 6.580343876034813, 
        "dso": 41.17968584164721, 
        "date": "2010-12-31", 
        "dpo": 15.003543586109142, 
        "gross_profit_margin": 10.146465718531097, 
        "ccc": 65.10775104363162
    }, 
    {
        "dio": 40.01137138958381, 
        "net_profit_margin": 6.565884476534296, 
        "net_profit_before_tax_margin": 6.97202166064982, 
        "operating_profit_margin": -2.707581227436823, 
        "dso": 64.85503158844766, 
        "date": "2011-12-31", 
        "dpo": 15.274050488969753, 
        "gross_profit_margin": 0.78971119133574, 
        "ccc": 89.59235248906171
    }, 
    {
        "dio": 40.48747417355372, 
        "net_profit_margin": -1.0877814318239312, 
        "net_profit_before_tax_margin": -0.8601062484189224, 
        "operating_profit_margin": -1.6190235264356183, 
        "dso": 65.97331140905641, 
        "date": "2012-12-31", 
        "dpo": 10.227918388429751, 
        "gross_profit_margin": 2.074373893245636, 
        "ccc": 96.23286719418037
    }, 
    {
        "dio": 35.02064048036027, 
        "net_profit_margin": 4.3042308632917585, 
        "net_profit_before_tax_margin": 4.817803864025434, 
        "operating_profit_margin": -1.6385424309122036, 
        "dso": 49.89850819271215, 
        "date": "2013-12-31", 
        "dpo": 4.7942206654991235, 
        "gross_profit_margin": 2.2254830031792614, 
        "ccc": 80.12492800757329
    }, 
    {
        "dio": 34.09856078129015, 
        "net_profit_margin": 4.351032448377581, 
        "net_profit_before_tax_margin": 5.11307767944936, 
        "operating_profit_margin": 0.09832841691248771, 
        "dso": 42.57436086529007, 
        "date": "2014-12-31", 
        "dpo": 3.3301207915702906, 
        "gross_profit_margin": 4.351032448377581, 
        "ccc": 73.34280085500993
    }
]