[
    {
        "dio": 104.90312163616792, 
        "net_profit_margin": 16.45539344654389, 
        "net_profit_before_tax_margin": 17.005501076297534, 
        "operating_profit_margin": 14.446304711791438, 
        "dso": 42.34034919875628, 
        "date": "2007-12-31", 
        "dpo": 79.49587369931827, 
        "gross_profit_margin": 33.34130590767759, 
        "ccc": 67.74759713560594
    }, 
    {
        "dio": 92.93294779618631, 
        "net_profit_margin": 13.13700918964077, 
        "net_profit_before_tax_margin": 15.64327485380117, 
        "operating_profit_margin": 10.79782790309106, 
        "dso": 32.170008354218886, 
        "date": "2008-12-31", 
        "dpo": 60.472022507033444, 
        "gross_profit_margin": 33.20802005012531, 
        "ccc": 64.63093364337175
    }, 
    {
        "dio": 115.43785786460087, 
        "net_profit_margin": 8.685189236490922, 
        "net_profit_before_tax_margin": 11.244804200393787, 
        "operating_profit_margin": 11.922992780573178, 
        "dso": 31.820717567271934, 
        "date": "2009-12-31", 
        "dpo": 82.24486359043449, 
        "gross_profit_margin": 35.047035659593085, 
        "ccc": 65.01371184143831
    }, 
    {
        "dio": 102.31185218566922, 
        "net_profit_margin": 13.298127700432069, 
        "net_profit_before_tax_margin": 15.77852456393023, 
        "operating_profit_margin": 10.81773083693391, 
        "dso": 33.35173627780445, 
        "date": "2010-12-31", 
        "dpo": 84.67045966651645, 
        "gross_profit_margin": 28.996639462313972, 
        "ccc": 50.99312879695722
    }, 
    {
        "dio": 80.21860328638498, 
        "net_profit_margin": 19.076026637069923, 
        "net_profit_before_tax_margin": 21.73973362930078, 
        "operating_profit_margin": 10.668701442841288, 
        "dso": 32.05396781354051, 
        "date": "2011-12-31", 
        "dpo": 92.21390845070424, 
        "gross_profit_margin": 29.078801331853498, 
        "ccc": 20.058662649221247
    }, 
    {
        "dio": 84.44922194922194, 
        "net_profit_margin": 18.414368650217707, 
        "net_profit_before_tax_margin": 19.829462989840348, 
        "operating_profit_margin": 11.175616835994195, 
        "dso": 41.65185050798259, 
        "date": "2012-12-31", 
        "dpo": 129.78774228774228, 
        "gross_profit_margin": 33.56313497822932, 
        "ccc": -3.6866698305377525
    }, 
    {
        "dio": 96.33012338248571, 
        "net_profit_margin": 22.822085889570552, 
        "net_profit_before_tax_margin": 28.057259713701434, 
        "operating_profit_margin": 8.425357873210634, 
        "dso": 56.95194274028629, 
        "date": "2013-12-31", 
        "dpo": 136.3120674089678, 
        "gross_profit_margin": 32.04498977505112, 
        "ccc": 16.969998713804188
    }, 
    {
        "dio": 76.85315087396503, 
        "net_profit_margin": 23.245958248312668, 
        "net_profit_before_tax_margin": 27.782137811960446, 
        "operating_profit_margin": 10.75184429445927, 
        "dso": 45.37435253492387, 
        "date": "2014-12-31", 
        "dpo": 115.59452621895124, 
        "gross_profit_margin": 31.753256945534453, 
        "ccc": 6.632977189937662
    }
]