[
    {
        "dio": 143.96833013435702, 
        "net_profit_margin": 1.6202203499675956, 
        "net_profit_before_tax_margin": -0.8425145819831497, 
        "operating_profit_margin": 0.06480881399870382, 
        "dso": 65.5249513933895, 
        "date": "2007-12-31", 
        "dpo": 92.4760076775432, 
        "gross_profit_margin": 32.469215813350615, 
        "ccc": 117.01727385020332
    }, 
    {
        "dio": 133.4179850124896, 
        "net_profit_margin": -1.4943215780035863, 
        "net_profit_before_tax_margin": -1.2552301255230125, 
        "operating_profit_margin": -0.2988643156007173, 
        "dso": 59.451583980872684, 
        "date": "2008-12-31", 
        "dpo": 67.16486261448793, 
        "gross_profit_margin": 28.212791392707707, 
        "ccc": 125.70470637887436
    }, 
    {
        "dio": 145.2820910973085, 
        "net_profit_margin": -0.21945866861741037, 
        "net_profit_before_tax_margin": -4.6086320409656185, 
        "operating_profit_margin": -2.6335040234089244, 
        "dso": 71.82516459400146, 
        "date": "2009-12-31", 
        "dpo": 68.76811594202898, 
        "gross_profit_margin": 29.261155815654718, 
        "ccc": 148.33913974928095
    }, 
    {
        "dio": 77.19128678592038, 
        "net_profit_margin": -2.5922671353251316, 
        "net_profit_before_tax_margin": -2.1528998242530757, 
        "operating_profit_margin": -0.39543057996485065, 
        "dso": 62.62412126537785, 
        "date": "2010-12-31", 
        "dpo": 60.868436237738024, 
        "gross_profit_margin": 23.857644991212652, 
        "ccc": 78.9469718135602
    }, 
    {
        "dio": 101.00808555033906, 
        "net_profit_margin": 2.8612821441506697, 
        "net_profit_before_tax_margin": 5.939876856211518, 
        "operating_profit_margin": 6.736689605215501, 
        "dso": 62.46378123868164, 
        "date": "2011-12-31", 
        "dpo": 68.54460093896714, 
        "gross_profit_margin": 30.5686345526983, 
        "ccc": 94.92726585005357
    }, 
    {
        "dio": 151.4787525702536, 
        "net_profit_margin": 7.8152753108348145, 
        "net_profit_before_tax_margin": 9.369449378330373, 
        "operating_profit_margin": 9.41385435168739, 
        "dso": 60.45515097690942, 
        "date": "2012-12-31", 
        "dpo": 69.7978067169294, 
        "gross_profit_margin": 35.213143872113676, 
        "ccc": 142.1360968302336
    }, 
    {
        "dio": 84.29136690647482, 
        "net_profit_margin": 8.116036505867015, 
        "net_profit_before_tax_margin": 10.691003911342895, 
        "operating_profit_margin": 11.538461538461538, 
        "dso": 51.63298565840939, 
        "date": "2013-12-31", 
        "dpo": 37.200239808153476, 
        "gross_profit_margin": 32.04041720990873, 
        "ccc": 98.72411275673073
    }, 
    {
        "dio": 94.95850028620492, 
        "net_profit_margin": 9.054103790945895, 
        "net_profit_before_tax_margin": 11.667280088332719, 
        "operating_profit_margin": 10.931174089068826, 
        "dso": 76.57342657342657, 
        "date": "2014-12-31", 
        "dpo": 53.38151116199199, 
        "gross_profit_margin": 35.70114096429886, 
        "ccc": 118.15041569763949
    }
]