[
    {
        "date": "2007-12-31", 
        "current_ratio": 1.1129032258064515, 
        "interest_protection_multiples": 25.4
    }, 
    {
        "date": "2008-12-31", 
        "current_ratio": 1.8774373259052926, 
        "interest_protection_multiples": 22.555555555555557
    }, 
    {
        "date": "2009-12-31", 
        "current_ratio": 1.8743016759776536, 
        "interest_protection_multiples": 29.428571428571427
    }, 
    {
        "date": "2010-12-31", 
        "current_ratio": 1.6970338983050848, 
        "interest_protection_multiples": 20.0
    }, 
    {
        "date": "2011-12-31", 
        "current_ratio": 1.3931972789115645, 
        "interest_protection_multiples": 15.571428571428571
    }, 
    {
        "date": "2012-12-31", 
        "current_ratio": 1.721835883171071, 
        "interest_protection_multiples": 14.818181818181818
    }, 
    {
        "date": "2013-12-31", 
        "current_ratio": 1.4462616822429906, 
        "quick_ratio": 0.8060747663551402, 
        "interest_protection_multiples": 14.727272727272727
    }, 
    {
        "date": "2014-12-31", 
        "current_ratio": 1.4091954022988507, 
        "quick_ratio": 0.732183908045977, 
        "interest_protection_multiples": 15.636363636363637
    }
]