[
    {
        "date": "2007-12-31", 
        "current_ratio": 2.661676646706587, 
        "quick_ratio": 1.811377245508982
    }, 
    {
        "date": "2008-12-31", 
        "current_ratio": 2.696319018404908, 
        "quick_ratio": 1.7699386503067485, 
        "interest_protection_multiples": 32.42857142857143
    }, 
    {
        "date": "2009-12-31", 
        "current_ratio": 2.283333333333333, 
        "interest_protection_multiples": 92.25
    }, 
    {
        "date": "2010-12-31", 
        "current_ratio": 3.6587301587301586, 
        "interest_protection_multiples": 126.0
    }, 
    {
        "date": "2011-12-31", 
        "current_ratio": 2.6430348258706466, 
        "interest_protection_multiples": 95.8
    }, 
    {
        "date": "2012-12-31", 
        "current_ratio": 3.448051948051948, 
        "interest_protection_multiples": 104.8
    }, 
    {
        "date": "2013-12-31", 
        "current_ratio": 2.466887417218543, 
        "interest_protection_multiples": 258.6666666666667
    }, 
    {
        "date": "2014-12-31", 
        "current_ratio": 2.749770852428964, 
        "interest_protection_multiples": 239.25
    }
]