[
    {
        "true_liabilities_ratio": 40.17905588714053, 
        "liabilities_ratio": 62.12857914640735, 
        "long_term_capital_to_fixed_assets_ratio": 0.8821068176224465, 
        "equity_multiplier": 2.6405135520684735, 
        "date": "2007-12-31", 
        "equity_ratio": 37.87142085359265
    }, 
    {
        "true_liabilities_ratio": 43.20203303684879, 
        "liabilities_ratio": 60.98810612991766, 
        "long_term_capital_to_fixed_assets_ratio": 0.9487496905174548, 
        "equity_multiplier": 2.5633208255159476, 
        "date": "2008-12-31", 
        "equity_ratio": 39.01189387008234
    }, 
    {
        "true_liabilities_ratio": 33.855421686746986, 
        "liabilities_ratio": 64.47614195958566, 
        "long_term_capital_to_fixed_assets_ratio": 0.8005974607916355, 
        "equity_multiplier": 2.8150095602294454, 
        "date": "2009-12-31", 
        "equity_ratio": 35.52385804041433
    }, 
    {
        "true_liabilities_ratio": 45.007641365257264, 
        "liabilities_ratio": 62.99567411679885, 
        "long_term_capital_to_fixed_assets_ratio": 0.9507217521154804, 
        "equity_multiplier": 2.702386751095957, 
        "date": "2010-12-31", 
        "equity_ratio": 37.004325883201155
    }, 
    {
        "true_liabilities_ratio": 46.85812469317624, 
        "liabilities_ratio": 63.589743589743584, 
        "long_term_capital_to_fixed_assets_ratio": 0.9766125061546036, 
        "equity_multiplier": 2.747813411078717, 
        "date": "2011-12-31", 
        "equity_ratio": 36.39257294429708
    }, 
    {
        "true_liabilities_ratio": 51.166111375535465, 
        "liabilities_ratio": 63.51681382678941, 
        "long_term_capital_to_fixed_assets_ratio": 1.075992637391533, 
        "equity_multiplier": 2.7409886714727087, 
        "date": "2012-12-31", 
        "equity_ratio": 36.4831861732106
    }, 
    {
        "true_liabilities_ratio": 42.81563655573164, 
        "liabilities_ratio": 60.30209140201394, 
        "long_term_capital_to_fixed_assets_ratio": 1.077194012327561, 
        "equity_multiplier": 2.5202537823328455, 
        "date": "2013-12-31", 
        "equity_ratio": 39.678543764523624
    }, 
    {
        "true_liabilities_ratio": 39.377085650723025, 
        "liabilities_ratio": 57.580115036976174, 
        "long_term_capital_to_fixed_assets_ratio": 1.0763760049474336, 
        "equity_multiplier": 2.3573849878934623, 
        "date": "2014-12-31", 
        "equity_ratio": 42.41988496302383
    }
]