[
    {
        "dio": 3406.666666666667, 
        "net_profit_margin": 473.87387387387383, 
        "net_profit_before_tax_margin": 496.3963963963964, 
        "operating_profit_margin": 495.4954954954955, 
        "dso": 2.4662162162162162, 
        "date": "2013-09-30", 
        "dpo": 315.75396825396825, 
        "gross_profit_margin": 43.24324324324324, 
        "ccc": 3093.378914628915
    }, 
    {
        "dio": 11397.125, 
        "net_profit_margin": -88.23529411764706, 
        "net_profit_before_tax_margin": -88.23529411764706, 
        "operating_profit_margin": -108.8235294117647, 
        "dso": 6.709558823529412, 
        "date": "2013-12-31", 
        "dpo": 1131.5, 
        "gross_profit_margin": 41.17647058823529, 
        "ccc": 10272.33455882353
    }, 
    {
        "dio": 42096.66666666667, 
        "net_profit_margin": -250.0, 
        "net_profit_before_tax_margin": -250.0, 
        "operating_profit_margin": -330.0, 
        "dso": 18.25, 
        "date": "2014-03-31", 
        "dpo": 4121.458333333334, 
        "gross_profit_margin": 40.0, 
        "ccc": 37993.458333333336
    }, 
    {
        "dio": 57870.75000000001, 
        "net_profit_margin": -471.42857142857144, 
        "net_profit_before_tax_margin": -457.1428571428571, 
        "operating_profit_margin": -814.2857142857142, 
        "dso": 45.625, 
        "date": "2014-06-30", 
        "dpo": 5976.875, 
        "gross_profit_margin": 42.857142857142854, 
        "ccc": 51939.50000000001
    }, 
    {
        "dio": 84805.46875, 
        "net_profit_margin": -1012.5, 
        "net_profit_before_tax_margin": -1000.0, 
        "operating_profit_margin": -787.5, 
        "dso": 96.953125, 
        "date": "2014-09-30", 
        "dpo": 8805.625, 
        "gross_profit_margin": 50.0, 
        "ccc": 76096.796875
    }, 
    {
        "dio": 76011.25000000001, 
        "net_profit_margin": -558.3333333333333, 
        "net_profit_before_tax_margin": -566.6666666666667, 
        "operating_profit_margin": -333.33333333333337, 
        "dso": 60.83333333333333, 
        "date": "2014-12-31", 
        "dpo": 6633.875, 
        "gross_profit_margin": 58.333333333333336, 
        "ccc": 69438.20833333334
    }, 
    {
        "dio": 74216.66666666666, 
        "net_profit_margin": -518.1818181818181, 
        "net_profit_before_tax_margin": -509.09090909090907, 
        "operating_profit_margin": -300.0, 
        "dso": 33.18181818181818, 
        "date": "2015-03-31", 
        "dpo": 5300.104166666667, 
        "gross_profit_margin": 45.45454545454545, 
        "ccc": 68949.74431818181
    }, 
    {
        "dio": 13130.641025641024, 
        "net_profit_margin": -118.75, 
        "net_profit_before_tax_margin": -108.33333333333333, 
        "operating_profit_margin": -87.5, 
        "dso": 60.83333333333333, 
        "date": "2015-06-30", 
        "dpo": 1000.2403846153846, 
        "gross_profit_margin": 18.75, 
        "ccc": 12191.233974358973
    }, 
    {
        "dio": 3896.311188811189, 
        "net_profit_margin": 20.30075187969925, 
        "net_profit_before_tax_margin": 22.18045112781955, 
        "operating_profit_margin": 29.69924812030075, 
        "dso": 18.18139097744361, 
        "date": "2015-09-30", 
        "dpo": 283.32167832167835, 
        "gross_profit_margin": 46.2406015037594, 
        "ccc": 3631.170901466954
    }
]