[
    {
        "dio": 51.79054054054054, 
        "net_profit_margin": 6.5420560747663545, 
        "net_profit_before_tax_margin": 4.672897196261682, 
        "operating_profit_margin": 4.672897196261682, 
        "dso": 69.07710280373831, 
        "date": "2013-09-30", 
        "dpo": 45.625, 
        "gross_profit_margin": 30.8411214953271, 
        "ccc": 75.24264334427886
    }, 
    {
        "dio": 68.0372807017544, 
        "net_profit_margin": 18.75, 
        "net_profit_before_tax_margin": 21.25, 
        "operating_profit_margin": -12.5, 
        "dso": 81.5546875, 
        "date": "2013-12-31", 
        "dpo": 48.82675438596491, 
        "gross_profit_margin": 28.749999999999996, 
        "ccc": 100.76521381578951
    }, 
    {
        "dio": 80.09722222222221, 
        "net_profit_margin": -16.666666666666664, 
        "net_profit_before_tax_margin": -16.666666666666664, 
        "operating_profit_margin": -20.0, 
        "dso": 78.32291666666667, 
        "date": "2014-03-31", 
        "dpo": 47.65277777777777, 
        "gross_profit_margin": 25.0, 
        "ccc": 110.76736111111111
    }, 
    {
        "dio": 45.625, 
        "net_profit_margin": 2.857142857142857, 
        "net_profit_before_tax_margin": 2.857142857142857, 
        "operating_profit_margin": 3.8095238095238098, 
        "dso": 52.14285714285714, 
        "date": "2014-06-30", 
        "dpo": 42.542229729729726, 
        "gross_profit_margin": 29.523809523809526, 
        "ccc": 55.22562741312741
    }, 
    {
        "dio": 46.1376404494382, 
        "net_profit_margin": 1.6260162601626018, 
        "net_profit_before_tax_margin": 2.4390243902439024, 
        "operating_profit_margin": 0.8130081300813009, 
        "dso": 63.80081300813007, 
        "date": "2014-09-30", 
        "dpo": 51.26404494382023, 
        "gross_profit_margin": 27.64227642276423, 
        "ccc": 58.67440851374804
    }, 
    {
        "dio": 48.390151515151516, 
        "net_profit_margin": 9.271523178807946, 
        "net_profit_before_tax_margin": 10.596026490066226, 
        "operating_profit_margin": 5.960264900662252, 
        "dso": 59.826158940397356, 
        "date": "2014-12-31", 
        "dpo": 58.989898989899, 
        "gross_profit_margin": 34.437086092715234, 
        "ccc": 49.22641146564987
    }, 
    {
        "dio": 53.390957446808514, 
        "net_profit_margin": 13.375796178343949, 
        "net_profit_before_tax_margin": 14.012738853503185, 
        "operating_profit_margin": 15.286624203821656, 
        "dso": 72.65127388535032, 
        "date": "2015-03-31", 
        "dpo": 64.06914893617021, 
        "gross_profit_margin": 40.12738853503185, 
        "ccc": 61.97308239598863
    }, 
    {
        "dio": 35.51819620253164, 
        "net_profit_margin": 13.247863247863249, 
        "net_profit_before_tax_margin": 12.82051282051282, 
        "operating_profit_margin": 14.102564102564102, 
        "dso": 65.31784188034189, 
        "date": "2015-06-30", 
        "dpo": 40.42721518987342, 
        "gross_profit_margin": 32.47863247863248, 
        "ccc": 60.40882289300011
    }
]