[
    {
        "dio": 78.79151291512915, 
        "net_profit_margin": 6.666666666666667, 
        "net_profit_before_tax_margin": 8.533333333333333, 
        "operating_profit_margin": 8.266666666666666, 
        "dso": 127.74999999999999, 
        "date": "2013-09-30", 
        "dpo": 57.57841328413284, 
        "gross_profit_margin": 27.73333333333333, 
        "ccc": 148.9630996309963
    }, 
    {
        "dio": 108.44202898550724, 
        "net_profit_margin": 6.397306397306397, 
        "net_profit_before_tax_margin": 8.417508417508419, 
        "operating_profit_margin": 5.05050505050505, 
        "dso": 150.08627946127945, 
        "date": "2013-12-31", 
        "dpo": 72.73550724637681, 
        "gross_profit_margin": 30.303030303030305, 
        "ccc": 185.79280120040988
    }, 
    {
        "dio": 108.04726368159203, 
        "net_profit_margin": 5.6537102473498235, 
        "net_profit_before_tax_margin": 6.713780918727916, 
        "operating_profit_margin": 4.946996466431095, 
        "dso": 136.55256183745584, 
        "date": "2014-03-31", 
        "dpo": 62.1952736318408, 
        "gross_profit_margin": 28.975265017667844, 
        "ccc": 182.40455188720708
    }, 
    {
        "dio": 82.53055555555557, 
        "net_profit_margin": 10.574018126888216, 
        "net_profit_before_tax_margin": 11.178247734138973, 
        "operating_profit_margin": 10.876132930513595, 
        "dso": 111.92598187311178, 
        "date": "2014-06-30", 
        "dpo": 51.50555555555555, 
        "gross_profit_margin": 32.02416918429003, 
        "ccc": 142.95098187311177
    }, 
    {
        "dio": 77.09051724137932, 
        "net_profit_margin": 12.643678160919542, 
        "net_profit_before_tax_margin": 15.229885057471265, 
        "operating_profit_margin": 11.494252873563218, 
        "dso": 114.84913793103448, 
        "date": "2014-09-30", 
        "dpo": 55.45797413793104, 
        "gross_profit_margin": 33.33333333333333, 
        "ccc": 136.48168103448273
    }, 
    {
        "dio": 85.19549763033176, 
        "net_profit_margin": 10.248447204968944, 
        "net_profit_before_tax_margin": 12.732919254658384, 
        "operating_profit_margin": 8.074534161490684, 
        "dso": 127.381599378882, 
        "date": "2014-12-31", 
        "dpo": 54.058056872037916, 
        "gross_profit_margin": 34.47204968944099, 
        "ccc": 158.51904013717584
    }, 
    {
        "dio": 88.19265463917526, 
        "net_profit_margin": 5.902777777777778, 
        "net_profit_before_tax_margin": 6.944444444444445, 
        "operating_profit_margin": 6.944444444444445, 
        "dso": 132.59765624999997, 
        "date": "2015-03-31", 
        "dpo": 47.741623711340196, 
        "gross_profit_margin": 32.63888888888889, 
        "ccc": 173.04868717783503
    }, 
    {
        "dio": 86.915625, 
        "net_profit_margin": 4.444444444444445, 
        "net_profit_before_tax_margin": 2.9629629629629632, 
        "operating_profit_margin": 0.3703703703703704, 
        "dso": 128.93287037037038, 
        "date": "2015-06-30", 
        "dpo": 47.45, 
        "gross_profit_margin": 26.296296296296294, 
        "ccc": 168.39849537037037
    }, 
    {
        "dio": 62.443627450980394, 
        "net_profit_margin": 13.812154696132598, 
        "net_profit_before_tax_margin": 16.298342541436465, 
        "operating_profit_margin": 7.18232044198895, 
        "dso": 106.12223756906079, 
        "date": "2015-09-30", 
        "dpo": 36.1421568627451, 
        "gross_profit_margin": 29.55801104972376, 
        "ccc": 132.42370815729606
    }
]