[
    {
        "dio": 73.11235708003518, 
        "net_profit_margin": 3.6004645760743323, 
        "net_profit_before_tax_margin": 8.091366627951995, 
        "operating_profit_margin": 9.059233449477352, 
        "dso": 61.04529616724738, 
        "date": "2013-09-30", 
        "dpo": 22.47141600703606, 
        "gross_profit_margin": 11.962833914053427, 
        "ccc": 111.6862372402465
    }, 
    {
        "dio": 84.89548192771085, 
        "net_profit_margin": 4.311846689895471, 
        "net_profit_before_tax_margin": 6.402439024390244, 
        "operating_profit_margin": 6.576655052264808, 
        "dso": 65.69523083623693, 
        "date": "2013-12-31", 
        "dpo": 27.726807228915664, 
        "gross_profit_margin": 9.625435540069686, 
        "ccc": 122.86390553503212
    }, 
    {
        "dio": 70.2606490872211, 
        "net_profit_margin": 6.1723886048210375, 
        "net_profit_before_tax_margin": 7.706355003652302, 
        "operating_profit_margin": 7.231555880204529, 
        "dso": 57.072909057706354, 
        "date": "2014-03-31", 
        "dpo": 23.89528397565923, 
        "gross_profit_margin": 9.970781592403213, 
        "ccc": 103.43827416926823
    }, 
    {
        "dio": 62.047086991221065, 
        "net_profit_margin": 7.032890132960112, 
        "net_profit_before_tax_margin": 8.432470258922322, 
        "operating_profit_margin": 9.482155353393981, 
        "dso": 59.46575402379286, 
        "date": "2014-06-30", 
        "dpo": 24.032322426177174, 
        "gross_profit_margin": 12.316305108467459, 
        "ccc": 97.48051858883674
    }, 
    {
        "dio": 66.42463235294117, 
        "net_profit_margin": 12.773591675636887, 
        "net_profit_before_tax_margin": 15.32113383566559, 
        "operating_profit_margin": 13.957660566917832, 
        "dso": 58.083064226767135, 
        "date": "2014-09-30", 
        "dpo": 27.01584126297578, 
        "gross_profit_margin": 17.04341585934697, 
        "ccc": 97.49185531673253
    }, 
    {
        "dio": 68.2008967156439, 
        "net_profit_margin": 13.060781476121564, 
        "net_profit_before_tax_margin": 14.688856729377713, 
        "operating_profit_margin": 13.350217076700435, 
        "dso": 54.55521888567294, 
        "date": "2014-12-31", 
        "dpo": 26.223530682800344, 
        "gross_profit_margin": 16.280752532561504, 
        "ccc": 96.5325849185165
    }, 
    {
        "dio": 68.45708154506438, 
        "net_profit_margin": 13.525575008582216, 
        "net_profit_before_tax_margin": 16.306213525575007, 
        "operating_profit_margin": 16.4778578784758, 
        "dso": 52.12495708891178, 
        "date": "2015-03-31", 
        "dpo": 26.591738197424895, 
        "gross_profit_margin": 20.013731548232062, 
        "ccc": 93.99030043655128
    }, 
    {
        "dio": 74.63079809004093, 
        "net_profit_margin": 12.201396545387725, 
        "net_profit_before_tax_margin": 15.61925762587284, 
        "operating_profit_margin": 16.1337743476663, 
        "dso": 56.89291620727674, 
        "date": "2015-06-30", 
        "dpo": 27.38744884038199, 
        "gross_profit_margin": 19.18412348401323, 
        "ccc": 104.13626545693567
    }, 
    {
        "dio": 92.60496671786994, 
        "net_profit_margin": 16.619831393014852, 
        "net_profit_before_tax_margin": 20.07226013649137, 
        "operating_profit_margin": 17.543155359293454, 
        "dso": 63.24493175431553, 
        "date": "2015-09-30", 
        "dpo": 28.03379416282642, 
        "gross_profit_margin": 21.637896427137697, 
        "ccc": 127.81610430935906
    }
]