[
    {
        "dio": 110.50814447592069, 
        "net_profit_margin": 1.63727959697733, 
        "net_profit_before_tax_margin": 2.0151133501259446, 
        "operating_profit_margin": 2.518891687657431, 
        "dso": 74.58595717884131, 
        "date": "2013-09-30", 
        "dpo": 73.80134560906515, 
        "gross_profit_margin": 11.083123425692696, 
        "ccc": 111.29275604569685
    }, 
    {
        "dio": 82.27726460071513, 
        "net_profit_margin": 2.569593147751606, 
        "net_profit_before_tax_margin": 3.4261241970021414, 
        "operating_profit_margin": 3.1049250535331905, 
        "dso": 67.36282119914347, 
        "date": "2013-12-31", 
        "dpo": 51.87872467222884, 
        "gross_profit_margin": 10.171306209850108, 
        "ccc": 97.76136112762974
    }, 
    {
        "dio": 85.05065554231227, 
        "net_profit_margin": 1.9313304721030045, 
        "net_profit_before_tax_margin": 2.682403433476395, 
        "operating_profit_margin": 2.467811158798283, 
        "dso": 73.33288626609442, 
        "date": "2014-03-31", 
        "dpo": 58.51311084624554, 
        "gross_profit_margin": 9.97854077253219, 
        "ccc": 99.87043096216114
    }, 
    {
        "dio": 86.08115468409586, 
        "net_profit_margin": 2.9069767441860463, 
        "net_profit_before_tax_margin": 3.875968992248062, 
        "operating_profit_margin": 3.9728682170542635, 
        "dso": 71.62063953488372, 
        "date": "2014-06-30", 
        "dpo": 59.93872549019608, 
        "gross_profit_margin": 11.046511627906977, 
        "ccc": 97.76306872878351
    }, 
    {
        "dio": 71.40611353711789, 
        "net_profit_margin": 2.0816653322658127, 
        "net_profit_before_tax_margin": 2.5620496397117694, 
        "operating_profit_margin": 2.321857485988791, 
        "dso": 71.04933947157727, 
        "date": "2014-09-30", 
        "dpo": 47.2985807860262, 
        "gross_profit_margin": 8.326661329063251, 
        "ccc": 95.15687222266894
    }, 
    {
        "dio": 91.91191709844558, 
        "net_profit_margin": 3.0499075785582255, 
        "net_profit_before_tax_margin": 3.8817005545286505, 
        "operating_profit_margin": 3.789279112754159, 
        "dso": 85.5152495378928, 
        "date": "2014-12-31", 
        "dpo": 53.568005181347154, 
        "gross_profit_margin": 10.905730129390019, 
        "ccc": 123.85916145499121
    }, 
    {
        "dio": 147.08774834437088, 
        "net_profit_margin": 2.9137529137529135, 
        "net_profit_before_tax_margin": 3.8461538461538463, 
        "operating_profit_margin": 3.263403263403263, 
        "dso": 95.8231351981352, 
        "date": "2015-03-31", 
        "dpo": 81.15811258278146, 
        "gross_profit_margin": 11.888111888111888, 
        "ccc": 161.75277095972464
    }, 
    {
        "dio": 117.13503228782288, 
        "net_profit_margin": 2.4207011686143574, 
        "net_profit_before_tax_margin": 3.33889816360601, 
        "operating_profit_margin": 3.1719532554257093, 
        "dso": 76.51137312186978, 
        "date": "2015-06-30", 
        "dpo": 73.44614852398523, 
        "gross_profit_margin": 9.515859766277128, 
        "ccc": 120.20025688570742
    }, 
    {
        "dio": 86.43920068027211, 
        "net_profit_margin": 2.533992583436341, 
        "net_profit_before_tax_margin": 3.15203955500618, 
        "operating_profit_margin": 3.955500618046971, 
        "dso": 78.81450865265761, 
        "date": "2015-09-30", 
        "dpo": 63.068027210884345, 
        "gross_profit_margin": 9.147095179233622, 
        "ccc": 102.18568212204536
    }
]