[
    {
        "true_liabilities_ratio": 18.545837723919917, 
        "liabilities_ratio": 50.03533568904594, 
        "long_term_capital_to_fixed_assets_ratio": 1.649859943977591, 
        "equity_multiplier": 2.0, 
        "date": "2013-09-30", 
        "equity_ratio": 50.0
    }, 
    {
        "true_liabilities_ratio": 16.070553650171483, 
        "liabilities_ratio": 49.0517518482803, 
        "long_term_capital_to_fixed_assets_ratio": 1.6649260226283724, 
        "equity_multiplier": 1.9627760252365931, 
        "date": "2013-12-31", 
        "equity_ratio": 50.948248151719696
    }, 
    {
        "true_liabilities_ratio": 17.92083514571553, 
        "liabilities_ratio": 49.00260190806591, 
        "long_term_capital_to_fixed_assets_ratio": 1.590643274853801, 
        "equity_multiplier": 1.9608843537414966, 
        "date": "2014-03-31", 
        "equity_ratio": 50.99739809193409
    }, 
    {
        "true_liabilities_ratio": 18.902743142144637, 
        "liabilities_ratio": 55.1673082617708, 
        "long_term_capital_to_fixed_assets_ratio": 1.3667870036101084, 
        "equity_multiplier": 2.2305151915455745, 
        "date": "2014-06-30", 
        "equity_ratio": 44.832691738229194
    }, 
    {
        "true_liabilities_ratio": 15.459882583170254, 
        "liabilities_ratio": 50.92620710598239, 
        "long_term_capital_to_fixed_assets_ratio": 1.3829634931997137, 
        "equity_multiplier": 2.0377475247524752, 
        "date": "2014-09-30", 
        "equity_ratio": 49.073792894017615
    }, 
    {
        "true_liabilities_ratio": 25.06790842064416, 
        "liabilities_ratio": 49.289495681248255, 
        "long_term_capital_to_fixed_assets_ratio": 1.7728253055355858, 
        "equity_multiplier": 1.971978021978022, 
        "date": "2014-12-31", 
        "equity_ratio": 50.71050431875174
    }, 
    {
        "true_liabilities_ratio": 27.70221904080172, 
        "liabilities_ratio": 48.87760555852485, 
        "long_term_capital_to_fixed_assets_ratio": 1.9485134155184916, 
        "equity_multiplier": 1.956089911134344, 
        "date": "2015-03-31", 
        "equity_ratio": 51.12239444147515
    }, 
    {
        "true_liabilities_ratio": 30.2471557473519, 
        "liabilities_ratio": 57.14285714285714, 
        "long_term_capital_to_fixed_assets_ratio": 1.7682838522809559, 
        "equity_multiplier": 2.3333333333333335, 
        "date": "2015-06-30", 
        "equity_ratio": 42.857142857142854
    }
]